clockbound/__init__.py
clockbound/clockbound.py
clockbound/errors.py
clockbound/py.typed
clockbound-0.3.0.dist-info/WHEEL
clockbound-0.3.0.dist-info/METADATA
clockbound-0.3.0.dist-info/RECORD
