Metadata-Version: 2.4
Name: clockbound
Version: 0.3.0
Summary: Add your description here
Author: Hunter Fernandes
Author-email: Hunter Fernandes <hgfern@gmail.com>
License-Expression: MIT
Classifier: Development Status :: 4 - Beta
Classifier: Programming Language :: Python
Requires-Python: >=3.13
Project-URL: Repository, https://github.com/hfern/clockbound
